vid2cleantxt/__init__.py
vid2cleantxt/audio2text_functions.py
vid2cleantxt/transcribe.py
vid2cleantxt/v2ct_utils.py
vid2cleantxt-0.0.2.data/data/LICENSE
vid2cleantxt-0.0.2.data/data/README.md
vid2cleantxt-0.0.2.data/data/requirements.txt
vid2cleantxt-0.0.2.dist-info/LICENSE
vid2cleantxt-0.0.2.dist-info/METADATA
vid2cleantxt-0.0.2.dist-info/WHEEL
vid2cleantxt-0.0.2.dist-info/top_level.txt
vid2cleantxt-0.0.2.dist-info/RECORD
