Metadata-Version: 2.1
Name: vid2cleantxt
Version: 0.0.2
Summary: A command-line tool to easily transcribe speech-based video files into clean text. also in Colab.
Home-page: https://github.com/pszemraj/vid2cleantxt
Author: Peter Szemraj, Jonathan Lehner
Author-email: szemraj.dev@gmail.com
License: UNKNOWN
Platform: UNKNOWN
Classifier: Programming Language :: Python :: 3
Classifier: License :: OSI Approved :: Apache Software License
Classifier: Development Status :: 3 - Alpha
Classifier: Operating System :: OS Independent
Classifier: Natural Language :: English
Classifier: Topic :: Text Processing
Requires-Python: >=3.7
License-File: LICENSE
Requires-Dist: setuptools (~=60.9.3)
Requires-Dist: librosa (~=0.8.1)
Requires-Dist: wordninja (~=2.0.0)
Requires-Dist: psutil (~=5.8.0)
Requires-Dist: natsort (~=7.1.1)
Requires-Dist: pandas (~=1.3.0)
Requires-Dist: moviepy (~=1.0.3)
Requires-Dist: transformers (~=4.15.0)
Requires-Dist: numpy (~=1.21.0)
Requires-Dist: pydub (~=0.24.1)
Requires-Dist: symspellpy (~=6.7.0)
Requires-Dist: joblib (~=1.0.1)
Requires-Dist: torch (~=1.9.0)
Requires-Dist: tqdm (~=4.43.0)
Requires-Dist: plotly (~=4.14.3)
Requires-Dist: yake (~=0.4.8)
Requires-Dist: pysbd (~=0.3.4)
Requires-Dist: clean-text
Requires-Dist: GPUtil (~=1.4.0)
Requires-Dist: humanize (~=3.13.1)
Requires-Dist: neuspell (~=1.0.0)
Requires-Dist: openpyxl (>=3)
Requires-Dist: unidecode (~=1.3.2)
Requires-Dist: urllib3 (~=1.26.8)
Requires-Dist: spacy (<4.0.0,>=3.0.0)
